setup.cfg
setup.py
configstr/__init__.py
configstr/__main__.py
configstr/example.py
configstr/exceptions.py
configstr/load.py
configstr.egg-info/PKG-INFO
configstr.egg-info/SOURCES.txt
configstr.egg-info/dependency_links.txt
configstr.egg-info/requires.txt
configstr.egg-info/top_level.txt