Metadata-Version: 1.1
Name: configstr
Version: 0.1.0
Summary: Python client for configstr
Home-page: https://github.com/configstr/python-client
Author: Christopher Durkin
Author-email: dev@configstr.io
License: ISC
Download-URL: https://github.com/configstr/python-client/tarball/0.1.0
Keywords: configuration
Platform: UNKNOWN
Classifier: Development Status :: 3 - Alpha
Classifier: Intended Audience :: Developers
Classifier: Topic :: Software Development
Classifier: License :: OSI Approved :: ISC License (ISCL)
Classifier: Programming Language :: Python :: 2
Classifier: Programming Language :: Python :: 2.7
Classifier: Programming Language :: Python :: 3
Classifier: Programming Language :: Python :: 3.5
